CHANGES.txt
LICENSE.txt
MANIFEST.in
README.rst
setup.py
mr3po/__init__.py
mr3po/common.py
mr3po/mysqldump.py
mr3po.egg-info/PKG-INFO
mr3po.egg-info/SOURCES.txt
mr3po.egg-info/dependency_links.txt
mr3po.egg-info/top_level.txt