Metadata-Version: 1.1
Name: mr3po
Version: 0.1.0
Summary: Line-based protocols for use with mrjob.
Home-page: http://github.com/Yelp/mr3po
Author: David Marin
Author-email: dave@yelp.com
License: Apache
Platform: UNKNOWN
Classifier: Development Status :: 3 - Alpha
Classifier: Intended Audience :: Developers
Classifier: License :: OSI Approved :: Apache Software License
Classifier: Natural Language :: English
Classifier: Operating System :: OS Independent
Classifier: Programming Language :: Python
Classifier: Programming Language :: Python :: 2.5
Classifier: Programming Language :: Python :: 2.6
Classifier: Programming Language :: Python :: 2.7
Classifier: Topic :: Database
Provides: mr3po
